dico/__init__.py
dico/api.py
dico/cache.py
dico/client.py
dico/exception.py
dico/handler.py
dico/utils.py
dico/base/__init__.py
dico/base/http.py
dico/base/model.py
dico/http/__init__.py
dico/http/async_http.py
dico/http/ratelimit.py
dico/http/request.py
dico/model/__init__.py
dico/model/application.py
dico/model/application_role_connection_metadata.py
dico/model/audit_log.py
dico/model/auto_moderation.py
dico/model/channel.py
dico/model/emoji.py
dico/model/event.py
dico/model/extras.py
dico/model/gateway.py
dico/model/guild.py
dico/model/guild_scheduled_event.py
dico/model/guild_template.py
dico/model/invite.py
dico/model/permission.py
dico/model/snowflake.py
dico/model/stage.py
dico/model/sticker.py
dico/model/user.py
dico/model/voice.py
dico/model/webhook.py
dico/model/interactions/__init__.py
dico/model/interactions/commands.py
dico/model/interactions/components.py
dico/model/interactions/interactions.py
dico/voice/__init__.py
dico/voice/audio.py
dico/voice/client.py
dico/voice/encryptor.py
dico/voice/opus.py
dico/voice/voice_socket.py
dico/voice/websocket.py
dico/voice/bin/AUTHORS
dico/voice/bin/COPYING
dico/voice/bin/opus-x64.dll
dico/voice/bin/opus-x86.dll
dico/ws/__init__.py
dico/ws/ratelimit.py
dico/ws/websocket.py
dico_api-0.0.38.dist-info/LICENSE
dico_api-0.0.38.dist-info/METADATA
dico_api-0.0.38.dist-info/WHEEL
dico_api-0.0.38.dist-info/top_level.txt
dico_api-0.0.38.dist-info/RECORD
