Metadata-Version: 2.1
Name: dico-api
Version: 0.0.38
Summary: Yet another Discord API wrapper for Python.
Home-page: https://github.com/dico-api/dico
Author: eunwoo1104
Author-email: choi@eunwoo.dev
Classifier: Programming Language :: Python :: 3
Requires-Python: >=3.7
License-File: LICENSE
Requires-Dist: aiohttp
Requires-Dist: requests
Provides-Extra: dev
Requires-Dist: sphinx ; extra == 'dev'
Requires-Dist: sphinx-press-theme ; extra == 'dev'
Requires-Dist: black ==23.10.1 ; extra == 'dev'
Requires-Dist: isort ==5.13.2 ; extra == 'dev'
Provides-Extra: voice
Requires-Dist: PyNaCl ; extra == 'voice'
